mathemagic/__init__.py
mathemagic-1.1.dist-info/LICENSE
mathemagic-1.1.dist-info/METADATA
mathemagic-1.1.dist-info/WHEEL
mathemagic-1.1.dist-info/top_level.txt
mathemagic-1.1.dist-info/RECORD
