Metadata-Version: 2.1
Name: mathemagic
Version: 1.1
Summary: Module containing a lot of general and commonly used mathematical functions.
Home-page: http://github.com/FireHead90544/mathemagic
Author: Rudransh Joshi
Author-email: rudranshjoshi1806@gmail.com
License: GNU GPL v3
Project-URL: Documentation, https://mathemagic.readthedocs.io/en/latest/
Project-URL: Issue tracker, https://github.com/FireHead90544/mathemagic/issues
Platform: UNKNOWN
